brodata/__init__.py
brodata/bhr.py
brodata/bro.py
brodata/cpt.py
brodata/dino.py
brodata/epc.py
brodata/frd.py
brodata/gar.py
brodata/gld.py
brodata/gm.py
brodata/gml.py
brodata/gmn.py
brodata/gmw.py
brodata/gpd.py
brodata/guf.py
brodata/plot.py
brodata/sad.py
brodata/sfr.py
brodata/util.py
brodata/version.py
brodata/webservices.py
brodata-0.1.4.dist-info/licenses/LICENSE
brodata-0.1.4.dist-info/METADATA
brodata-0.1.4.dist-info/WHEEL
brodata-0.1.4.dist-info/top_level.txt
brodata-0.1.4.dist-info/RECORD
